airborne_antara/__init__.py
airborne_antara/__main__.py
airborne_antara/adapters.py
airborne_antara/consciousness_v2.py
airborne_antara/core.py
airborne_antara/health_monitor.py
airborne_antara/integration_guide.py
airborne_antara/memory.py
airborne_antara/meta_controller.py
airborne_antara/moe.py
airborne_antara/perception.py
airborne_antara/presets.py
airborne_antara/production.py
airborne_antara/self_awareness_v2.py
airborne_antara/validation.py
airborne_antara/world_model.py
airborne_antara-0.0.2.dist-info/licenses/LICENSE
airborne_antara-0.0.2.dist-info/METADATA
airborne_antara-0.0.2.dist-info/WHEEL
airborne_antara-0.0.2.dist-info/entry_points.txt
airborne_antara-0.0.2.dist-info/top_level.txt
airborne_antara-0.0.2.dist-info/RECORD
