Metadata-Version: 2.4
Name: airborne-antara
Version: 0.0.2
Summary: Production-grade adaptive meta-learning framework for continual model improvement. Implements research DOI: 10.5281/zenodo.17839490.
Author-email: AirborneHRS Team <friday@airbornehrs.in>
License-Expression: MIT
Project-URL: Homepage, https://github.com/Ultron09/Mirror_mind
Project-URL: Documentation, https://github.com/Ultron09/Mirror_mind#readme
Project-URL: Repository, https://github.com/Ultron09/Mirror_mind.git
Project-URL: Issues, https://github.com/Ultron09/Mirror_mind/issues
Project-URL: Research Paper, https://doi.org/10.5281/zenodo.17839490
Keywords: meta-learning,online-learning,continual-learning,adaptive-optimization,production-ml,automl,pytorch,deep-learning,self-healing-systems,neural-networks,model-monitoring
Classifier: Development Status :: 4 - Beta
Classifier: Intended Audience :: Developers
Classifier: Intended Audience :: Science/Research
Classifier: Intended Audience :: Information Technology
Classifier: Programming Language :: Python :: 3.10
Classifier: Programming Language :: Python :: 3.11
Classifier: Topic :: Scientific/Engineering :: Artificial Intelligence
Classifier: Topic :: Scientific/Engineering :: Information Analysis
Classifier: Topic :: System :: Monitoring
Classifier: Topic :: Software Development :: Libraries :: Python Modules
Requires-Python: >=3.8
License-File: LICENSE
Requires-Dist: torch>=2.0.0
Requires-Dist: numpy>=1.24.0
Requires-Dist: matplotlib>=3.7.0
Requires-Dist: tensorboard>=2.12.0
Requires-Dist: rich
Provides-Extra: dev
Requires-Dist: pytest>=7.4.0; extra == "dev"
Requires-Dist: pytest-cov>=4.0.0; extra == "dev"
Requires-Dist: black>=23.0; extra == "dev"
Requires-Dist: isort>=5.12.0; extra == "dev"
Requires-Dist: flake8>=6.0.0; extra == "dev"
Dynamic: license-file
